princo_ml/__init__.py
princo_ml/clusters/DataCluster.py
princo_ml/clusters/LearnCluster.py
princo_ml/clusters/MergeCluster.py
princo_ml/clusters/RootCluster.py
princo_ml/clusters/__init__.py
princo_ml/controllers/Controller.py
princo_ml/controllers/__init__.py
princo_ml/utils/__init__.py
princo_ml/utils/batchers/FlatBatch.py
princo_ml/utils/batchers/LowestBatch.py
princo_ml/utils/batchers/RootBatch.py
princo_ml/utils/batchers/__init__.py
princo_ml/utils/initialisers/FlatInit.py
princo_ml/utils/initialisers/HingeInit.py
princo_ml/utils/initialisers/NormalInit.py
princo_ml/utils/initialisers/OrthoInit.py
princo_ml/utils/initialisers/RootInit.py
princo_ml/utils/initialisers/__init__.py
princo_ml/utils/learn_modules/DenseHingeModule.py
princo_ml/utils/learn_modules/DenseModule.py
princo_ml/utils/learn_modules/RootModule.py
princo_ml/utils/learn_modules/__init__.py
princo_ml/utils/learn_modules/activators/LinearActivator.py
princo_ml/utils/learn_modules/activators/ReluActivator.py
princo_ml/utils/learn_modules/activators/RootActivator.py
princo_ml/utils/learn_modules/activators/SigmoidActivator.py
princo_ml/utils/learn_modules/activators/SoftMaxActivator.py
princo_ml/utils/learn_modules/activators/SoftReluActivator.py
princo_ml/utils/learn_modules/activators/TanhActivator.py
princo_ml/utils/learn_modules/activators/__init__.py
princo_ml/utils/learn_modules/combiners/HingeCombiner.py
princo_ml/utils/learn_modules/combiners/RootCombiner.py
princo_ml/utils/learn_modules/combiners/SimpleCombiner.py
princo_ml/utils/learn_modules/combiners/__init__.py
princo_ml/utils/learn_modules/learn_noise/RootLearnNoise.py
princo_ml/utils/learn_modules/learn_noise/StochasticLearnNoise.py
princo_ml/utils/learn_modules/learn_noise/__init__.py
princo_ml/utils/learn_modules/learn_rates/ExpDecayLearnRate.py
princo_ml/utils/learn_modules/learn_rates/FlatLearnRate.py
princo_ml/utils/learn_modules/learn_rates/RootLearnRate.py
princo_ml/utils/learn_modules/learn_rates/StepDecayLearnRate.py
princoml-0.1.0.dist-info/LICENSE
princoml-0.1.0.dist-info/METADATA
princoml-0.1.0.dist-info/WHEEL
princoml-0.1.0.dist-info/top_level.txt
princoml-0.1.0.dist-info/RECORD
