Metadata-Version: 2.1
Name: princoml
Version: 0.1.0
Summary: Custom neural network code.
Home-page: https://github.com/Calvinxc1/PrincoML
Author: Jason M. Cherry
Author-email: jcherry@gmail.com
License: UNKNOWN
Platform: UNKNOWN
Classifier: Programming Language :: Python :: 3
Classifier: License :: OSI Approved :: GNU General Public License (GPL)
Classifier: Operating System :: OS Independent
Requires-Python: >=3.6
Requires-Dist: numpy (<2.0.0,>=1.18.0)
Requires-Dist: pandas (<2.0.0,>=1.0.0)
Requires-Dist: torch (<2.0.0,>=1.4.0)
Requires-Dist: tqdm (<5.0.0,>=4.45.0)
Requires-Dist: matplotlib (<4.0.0,>=3.2.0)
